{
  "type": "FeatureCollection",
  "features": [
    {
      "type": "Feature",
      "geometry": {
        "type": "Point",
        "coordinates": [
          107.6067877,
          -6.9301452
        ]
      },
      "properties": {
        "id": 11883812981,
        "bus": "yes",
        "name": "SDN Moh. Toha",
        "public_transport": "stop_position"
      }
    }
  ]
}