{"type":"FeatureCollection","features":[{"type":"Feature","geometry":{"type":"Point","coordinates":[107.6067877,-6.9301452]},"properties":{"id":11883812981,"bus":"yes","name":"SDN Moh. Toha","public_transport":"stop_position"}},{"type":"Feature","geometry":{"type":"Point","coordinates":[107.798194,-6.9057915]},"properties":{"id":12629197814,"bus":"yes","public_transport":"stop_position"}}]}