{"type":"FeatureCollection","features":[{"type":"Feature","geometry":{"type":"Point","coordinates":[107.565655,-6.9487566]},"properties":{"id":3115112896,"bus":"yes","name":"Mesjid Jami Al Hamidah Cibolerang","public_transport":"stop_position"}},{"type":"Feature","geometry":{"type":"Point","coordinates":[107.6868117,-6.9655502]},"properties":{"id":2518053983,"bus":"yes","highway":"bus_stop","name":"Simpang Derwati","public_transport":"stop_position"}}]}