{"type":"FeatureCollection","features":[{"type":"Feature","geometry":{"type":"Point","coordinates":[107.7534452,-6.9398116]},"properties":{"id":10771913961,"bus":"yes","name":"Terminal Cileunyi","public_transport":"stop_position"}},{"type":"Feature","geometry":{"type":"Point","coordinates":[107.8916538,-7.0213162]},"properties":{"id":6382607283,"bus":"yes","name":"Perlintasan Kereta Api Nagreg","public_transport":"stop_position"}}]}