{
  "type": "FeatureCollection",
  "features": [
    {
      "type": "Feature",
      "geometry": {
        "type": "Point",
        "coordinates": [
          107.7534452,
          -6.9398116
        ]
      },
      "properties": {
        "id": 10771913961,
        "bus": "yes",
        "name": "Terminal Cileunyi",
        "public_transport": "stop_position"
      }
    },
    {
      "type": "Feature",
      "geometry": {
        "type": "Point",
        "coordinates": [
          107.6568007,
          -6.9022123
        ]
      },
      "properties": {
        "id": 5832221936,
        "bus": "yes",
        "name": "Depan Terminal Cicaheum",
        "public_transport": "stop_position"
      }
    }
  ]
}