{"type":"FeatureCollection","features":[{"type":"Feature","geometry":{"type":"Point","coordinates":[107.7534452,-6.9398116]},"properties":{"id":10771913961,"bus":"yes","name":"Terminal Cileunyi","public_transport":"stop_position"}},{"type":"Feature","geometry":{"type":"Point","coordinates":[107.6568631,-6.9021978]},"properties":{"id":5832221936,"bus":"yes","highway":"bus_stop","name":"Depan Terminal Cicaheum","public_transport":"stop_position","ref":"Terminal Cicaheum"}}]}