{"type":"FeatureCollection","features":[{"type":"Feature","geometry":{"type":"Point","coordinates":[107.6992861,-6.9158662]},"properties":{"id":12638331186,"bus":"yes","name":"RSUD Ujungberung","public_transport":"stop_position"}},{"type":"Feature","geometry":{"type":"Point","coordinates":[107.5755283,-6.9139507]},"properties":{"id":12013198354,"bus":"yes","public_transport":"stop_position"}}]}