{"type":"FeatureCollection","features":[{"type":"Feature","geometry":{"type":"Point","coordinates":[107.6429873,-6.9139486]},"properties":{"id":10815121105,"bus":"yes","departures_board":"no","highway":"bus_stop","name":"Flyover Antapani","public_transport":"platform","shelter":"yes","source":"POI_WRI_Survey_2023","wheelchair":"no"}},{"type":"Feature","geometry":{"type":"Point","coordinates":[107.5932351,-6.9459075]},"properties":{"id":10693001605,"bus":"yes","name":"Terminal Leuwipanjang","name:ar":"محطه باصات بندوق","public_transport":"stop_position"}}]}