{
  "type": "FeatureCollection",
  "features": [
    {
      "type": "Feature",
      "geometry": {
        "type": "Point",
        "coordinates": [
          107.5929891,
          -7.0463081
        ]
      },
      "properties": {
        "id": 12643871709,
        "bus": "yes",
        "name": "Simpang Bojong Pulus",
        "public_transport": "stop_position"
      }
    },
    {
      "type": "Feature",
      "geometry": {
        "type": "Point",
        "coordinates": [
          107.651034,
          -7.0580362
        ]
      },
      "properties": {
        "id": 12643871707,
        "bus": "yes",
        "name": "Pasar Arjasari",
        "public_transport": "stop_position"
      }
    }
  ]
}