{
  "type": "FeatureCollection",
  "features": [
    {
      "type": "Feature",
      "geometry": {
        "type": "Point",
        "coordinates": [
          107.3770315,
          -6.9601649
        ]
      },
      "properties": {
        "id": 5847986979,
        "bus": "yes",
        "name": "Pasar Cijenuk",
        "public_transport": "stop_position"
      }
    },
    {
      "type": "Feature",
      "geometry": {
        "type": "Point",
        "coordinates": [
          107.4573026,
          -6.9510754
        ]
      },
      "properties": {
        "id": 13446617201,
        "bus": "yes",
        "name": "Alun-alun Cililin",
        "public_transport": "stop_position"
      }
    }
  ]
}