{"type":"FeatureCollection","features":[{"type":"Feature","geometry":{"type":"Point","coordinates":[107.6252674,-6.8911775]},"properties":{"id":3252929646,"bus":"yes","highway":"bus_stop","name":"Terminal Sadang Serang","public_transport":"stop_position","ref":"Terminal Sadang Serang"}},{"type":"Feature","geometry":{"type":"Point","coordinates":[107.5879339,-6.9467105]},"properties":{"id":7484309659,"bus":"yes","name":"Barat Simpang Kopo Caringin","public_transport":"stop_position"}}]}