{
  "type": "FeatureCollection",
  "generator": "overpass-turbo",
  "copyright": "The data included in this document is from www.openstreetmap.org. The data is made available under ODbL.",
  "timestamp": "2025-03-05T10:10:40Z",
  "features": [
    {
      "type": "Feature",
      "properties": {
        "@id": "node/11711326973",
        "bus": "yes",
        "name": "Terminal Elang",
        "public_transport": "stop_position"
      },
      "geometry": {
        "type": "Point",
        "coordinates": [
          107.575723,
          -6.9133498
        ]
      },
      "id": "node/11711326973"
    },
    {
      "type": "Feature",
      "properties": {
        "@id": "node/6460801785",
        "bus": "yes",
        "name": "Terminal Cicaheum",
        "network": "Trans Metro Bandung",
        "operator": "Dinas Perhubungan Kota Bandung",
        "public_transport": "stop_position"
      },
      "geometry": {
        "type": "Point",
        "coordinates": [
          107.6565637,
          -6.902329
        ]
      },
      "id": "node/6460801785"
    }
  ]
}
