{
  "type": "FeatureCollection",
  "features": [
    {
      "type": "Feature",
      "geometry": {
        "type": "Point",
        "coordinates": [
          107.575723,
          -6.9133498
        ]
      },
      "properties": {
        "id": 11711326973,
        "bus": "yes",
        "name": "Terminal Elang",
        "public_transport": "stop_position"
      }
    },
    {
      "type": "Feature",
      "geometry": {
        "type": "Point",
        "coordinates": [
          107.650154,
          -6.9050722
        ]
      },
      "properties": {
        "id": 11735248708,
        "bus": "yes",
        "name": "Cimuncang",
        "public_transport": "stop_position"
      }
    }
  ]
}