{"type":"FeatureCollection","features":[{"type":"Feature","geometry":{"type":"Point","coordinates":[107.6024135,-6.9161558]},"properties":{"id":1013407725,"alt_name":"Stasiun Bandung Pintu Selatan","bus":"yes","highway":"bus_stop","name":"Stasiun Hall","public_transport":"stop_position","ref":"Stasiun Hall/Kebon Jati"}},{"type":"Feature","geometry":{"type":"Point","coordinates":[107.5673186,-6.8873601]},"properties":{"id":3250402136,"bus":"yes","highway":"bus_stop","name":"Gunung Batu","public_transport":"stop_position","ref":"Gunung Batu"}}]}