{"type":"FeatureCollection","features":[{"type":"Feature","geometry":{"type":"Point","coordinates":[107.5885486,-6.9141236]},"properties":{"id":3244745033,"amenity":"bus_station","bus":"yes","highway":"bus_stop","name":"Terminal Ciroyom","public_transport":"stop_position","ref":"Terminal Ciroyom"}},{"type":"Feature","geometry":{"type":"Point","coordinates":[107.6258024,-6.9189956]},"properties":{"id":12637510528,"bus":"yes","name":"Stasiun Cikudapateuh","public_transport":"stop_position"}}]}