{
  "type": "FeatureCollection",
  "features": [
    {
      "type": "Feature",
      "geometry": {
        "type": "Point",
        "coordinates": [
          107.5753653,
          -6.9129722
        ]
      },
      "properties": {
        "id": 11711326972,
        "bus": "yes",
        "name": "Plaza Telkom Rajawali",
        "public_transport": "stop_position"
      }
    },
    {
      "type": "Feature",
      "geometry": {
        "type": "Point",
        "coordinates": [
          107.5917121,
          -6.9165436
        ]
      },
      "properties": {
        "id": 11735239268,
        "bus": "yes",
        "name": "SMA Trinitas",
        "public_transport": "stop_position"
      }
    },
    {
      "type": "Feature",
      "geometry": {
        "type": "Point",
        "coordinates": [
          107.6258024,
          -6.9189956
        ]
      },
      "properties": {
        "id": 12637510528,
        "bus": "yes",
        "name": "Stasiun Cikudapateuh",
        "public_transport": "stop_position"
      }
    }
  ]
}