{
  "type": "FeatureCollection",
  "features": [
    {
      "type": "Feature",
      "geometry": {
        "type": "Point",
        "coordinates": [
          107.63163,
          -7.0796088
        ]
      },
      "properties": {
        "id": 12643871706,
        "bus": "yes",
        "name": "Pangkalan Angkot Ciburuy",
        "public_transport": "stop_position"
      }
    },
    {
      "type": "Feature",
      "geometry": {
        "type": "Point",
        "coordinates": [
          107.5867226,
          -7.0478629
        ]
      },
      "properties": {
        "id": 2477245043,
        "bus": "yes",
        "name": "Terminal Banjaran",
        "public_transport": "stop_position"
      }
    }
  ]
}