{
  "type": "FeatureCollection",
  "features": [
    {
      "type": "Feature",
      "geometry": {
        "type": "Point",
        "coordinates": [
          107.4983378,
          -6.8445013
        ]
      },
      "properties": {
        "id": 3115002514,
        "bus": "yes",
        "name": "Underpass Padalarang",
        "public_transport": "stop_position"
      }
    },
    {
      "type": "Feature",
      "geometry": {
        "type": "Point",
        "coordinates": [
          107.5820477,
          -6.8029839
        ]
      },
      "properties": {
        "id": 634455271,
        "bus": "yes",
        "highway": "bus_stop",
        "name": "Terminal Parongpong",
        "public_transport": "stop_position",
        "ref": "Terminal Parongpong"
      }
    }
  ]
}