{
  "type": "FeatureCollection",
  "features": [
    {
      "type": "Feature",
      "geometry": {
        "type": "Point",
        "coordinates": [
          107.4698419,
          -7.0992547
        ]
      },
      "properties": {
        "id": 12647548214,
        "bus": "yes",
        "name": "Terminal Cibeureum Ciwidey",
        "public_transport": "stop_position"
      }
    },
    {
      "type": "Feature",
      "geometry": {
        "type": "Point",
        "coordinates": [
          107.5930651,
          -6.9449801
        ]
      },
      "properties": {
        "id": 3115012017,
        "bus": "yes",
        "name": "Terminal Leuwipanjang",
        "public_transport": "stop_position"
      }
    }
  ]
}