{
  "type": "FeatureCollection",
  "features": [
    {
      "type": "Feature",
      "geometry": {
        "type": "Point",
        "coordinates": [
          107.6024325,
          -6.9161432
        ]
      },
      "properties": {
        "id": 1013407725,
        "alt_name": "Stasiun Bandung Pintu Selatan",
        "bus": "yes",
        "name": "Stasiun Hall",
        "public_transport": "stop_position"
      }
    },
    {
      "type": "Feature",
      "geometry": {
        "type": "Point",
        "coordinates": [
          107.6658787,
          -6.9149864
        ]
      },
      "properties": {
        "id": 11735248698,
        "bus": "yes",
        "name": "Depan Terminal Antapani",
        "public_transport": "stop_position"
      }
    }
  ]
}