{
  "type": "FeatureCollection",
  "features": [
    {
      "type": "Feature",
      "geometry": {
        "type": "Point",
        "coordinates": [
          107.5971615,
          -7.0180016
        ]
      },
      "properties": {
        "id": 549732638,
        "bus": "yes",
        "highway": "bus_stop",
        "name": "Asem Pameungpeuk",
        "public_transport": "stop_position"
      }
    },
    {
      "type": "Feature",
      "geometry": {
        "type": "Point",
        "coordinates": [
          107.593435,
          -6.9627318
        ]
      },
      "properties": {
        "id": 3248927104,
        "bus": "yes",
        "highway": "bus_stop",
        "name": "Cibaduyut",
        "public_transport": "stop_position",
        "ref": "Cibaduyut"
      }
    }
  ]
}