{
  "type": "FeatureCollection",
  "features": [
    {
      "type": "Feature",
      "geometry": {
        "type": "Point",
        "coordinates": [
          107.502891,
          -6.8977261
        ]
      },
      "properties": {
        "id": 1783118766,
        "bus": "yes",
        "highway": "bus_stop",
        "name": "Pangkalan Angkot Cangkorah",
        "public_transport": "stop_position"
      }
    }
  ]
}