{
  "type": "FeatureCollection",
  "features": [
    {
      "type": "Feature",
      "geometry": {
        "type": "Point",
        "coordinates": [
          107.6562486,
          -6.9024172
        ]
      },
      "properties": {
        "id": 11291524413,
        "bus": "yes",
        "name": "Terminal Angkot Cicaheum",
        "public_transport": "stop_position"
      }
    },
    {
      "type": "Feature",
      "geometry": {
        "type": "Point",
        "coordinates": [
          107.5951942,
          -6.85933
        ]
      },
      "properties": {
        "id": 11711070002,
        "bus": "yes",
        "name": "Terminal Ledeng",
        "public_transport": "stop_position"
      }
    }
  ]
}