{
  "type": "FeatureCollection",
  "features": [
    {
      "type": "Feature",
      "geometry": {
        "type": "Point",
        "coordinates": [
          107.9256435,
          -6.8441164
        ]
      },
      "properties": {
        "id": 3193640122,
        "bus": "yes",
        "highway": "bus_stop",
        "name": "Subterminal Ketib Sumedang",
        "public_transport": "stop_position"
      }
    },
    {
      "type": "Feature",
      "geometry": {
        "type": "Point",
        "coordinates": [
          107.7537453,
          -6.9404081
        ]
      },
      "properties": {
        "id": 6473170574,
        "bus": "yes",
        "name": "Pasar Cileunyi",
        "public_transport": "stop_position"
      }
    }
  ]
}