{
  "type": "FeatureCollection",
  "features": [
    {
      "type": "Feature",
      "geometry": {
        "type": "Point",
        "coordinates": [
          107.6071455,
          -6.9211653
        ]
      },
      "properties": {
        "id": 11711275743,
        "bus": "yes",
        "name": "Alun-Alun Bandung",
        "public_transport": "stop_position"
      }
    },
    {
      "type": "Feature",
      "geometry": {
        "type": "Point",
        "coordinates": [
          107.6065186,
          -6.9205454
        ]
      },
      "properties": {
        "id": 12808912264,
        "bus": "yes",
        "name": "Pos Banceuy",
        "public_transport": "stop_position"
      }
    },
    {
      "type": "Feature",
      "geometry": {
        "type": "Point",
        "coordinates": [
          107.4554476,
          -6.8818457
        ]
      },
      "properties": {
        "id": 5509730969,
        "bus": "yes",
        "name": "Tatar Subanglarang",
        "public_transport": "stop_position"
      }
    }
  ]
}