{
  "type": "FeatureCollection",
  "features": [
    {
      "type": "Feature",
      "geometry": {
        "type": "Point",
        "coordinates": [
          107.6438226,
          -6.9146708
        ]
      },
      "properties": {
        "id": 12633822765,
        "bus": "yes",
        "name": "Seberang Kiara Artha",
        "public_transport": "stop_position"
      }
    },
    {
      "type": "Feature",
      "geometry": {
        "type": "Point",
        "coordinates": [
          107.5934341,
          -6.9468277
        ]
      },
      "properties": {
        "id": 11295303565,
        "bus": "yes",
        "name": "Leuwipanjang Soekarno Hatta",
        "public_transport": "stop_position"
      }
    }
  ]
}