{"type":"FeatureCollection","features":[{"type":"Feature","geometry":{"type":"Point","coordinates":[107.6058931,-6.9273804]},"properties":{"id":3374033509,"amenity":"bus_station","bus":"yes","highway":"bus_stop","name":"Terminal Abdul Muis/Kebon Kalapa","public_transport":"stop_position","ref":"Terminal Abdul Muis/Kebon Kalapa"}},{"type":"Feature","geometry":{"type":"Point","coordinates":[107.5951798,-6.8790317]},"properties":{"id":12634504453,"bus":"yes","name":"Karangsetra Waterland","public_transport":"stop_position"}}]}