{
  "type": "FeatureCollection",
  "features": [
    {
      "type": "Feature",
      "geometry": {
        "type": "Point",
        "coordinates": [
          107.5951798,
          -6.8790317
        ]
      },
      "properties": {
        "id": 12634504453,
        "bus": "yes",
        "name": "Karangsetra Waterland",
        "public_transport": "stop_position"
      }
    },
    {
      "type": "Feature",
      "geometry": {
        "type": "Point",
        "coordinates": [
          107.6059095,
          -6.9275213
        ]
      },
      "properties": {
        "id": 3374033509,
        "amenity": "bus_station",
        "bus": "yes",
        "name": "Terminal Abdul Muis/Kebon Kalapa",
        "public_transport": "stop_position"
      }
    }
  ]
}