{
  "type": "FeatureCollection",
  "features": [
    {
      "type": "Feature",
      "geometry": {
        "type": "Point",
        "coordinates": [
          107.6664238,
          -6.9611563
        ]
      },
      "properties": {
        "id": 2258306743,
        "bus": "yes",
        "name": "Pasar Ciwastra",
        "public_transport": "stop_position"
      }
    },
    {
      "type": "Feature",
      "geometry": {
        "type": "Point",
        "coordinates": [
          107.6773057,
          -6.9389794
        ]
      },
      "properties": {
        "id": 13064974005,
        "bus": "yes",
        "name": "Bulog Kancab Bandung",
        "public_transport": "stop_position"
      }
    }
  ]
}