{"type":"FeatureCollection","features":[{"type":"Feature","geometry":{"type":"Point","coordinates":[107.5937757,-6.9617658]},"properties":{"id":11338633720,"bus":"yes","name":"Terminal Cibaduyut","public_transport":"stop_position"}},{"type":"Feature","geometry":{"type":"Point","coordinates":[107.6058931,-6.9273804]},"properties":{"id":3374033509,"amenity":"bus_station","bus":"yes","highway":"bus_stop","name":"Terminal Abdul Muis/Kebon Kalapa","public_transport":"stop_position","ref":"Terminal Abdul Muis/Kebon Kalapa"}}]}