{
  "type": "FeatureCollection",
  "features": [
    {
      "type": "Feature",
      "geometry": {
        "type": "Point",
        "coordinates": [
          107.6866274,
          -6.9667195
        ]
      },
      "properties": {
        "id": 2518053983,
        "bus": "yes",
        "name": "Simpang Derwati",
        "public_transport": "stop_position"
      }
    },
    {
      "type": "Feature",
      "geometry": {
        "type": "Point",
        "coordinates": [
          107.6199195,
          -6.9011743
        ]
      },
      "properties": {
        "id": 1666155324,
        "bus": "yes",
        "name": "Lapangan Gasibu A",
        "public_transport": "stop_position"
      }
    }
  ]
}