{"type":"FeatureCollection","features":[{"type":"Feature","geometry":{"type":"Point","coordinates":[107.5829792,-6.9419021]},"properties":{"id":12633822769,"bus":"yes","name":"Pasar Caringin","public_transport":"stop_position"}},{"type":"Feature","geometry":{"type":"Point","coordinates":[107.6209442,-6.866704]},"properties":{"id":3373712056,"bench":"no","covered":"no","highway":"bus_stop","name":"Terminal Dago","operator":"Angkot Kota Bandung","public_transport":"stop_position","shelter":"no"}}]}