{"type":"FeatureCollection","features":[{"type":"Feature","geometry":{"type":"Point","coordinates":[107.5379919,-6.8807505]},"properties":{"id":9668839346,"bus":"yes","highway":"bus_stop","name":"Pasar Antri","public_transport":"platform"}},{"type":"Feature","geometry":{"type":"Point","coordinates":[107.6024135,-6.9161558]},"properties":{"id":1013407725,"alt_name":"Stasiun Bandung Pintu Selatan","bus":"yes","highway":"bus_stop","name":"Stasiun Hall","public_transport":"stop_position","ref":"Stasiun Hall/Kebon Jati"}}]}