{
  "type": "FeatureCollection",
  "features": [
    {
      "type": "Feature",
      "geometry": {
        "type": "Point",
        "coordinates": [
          107.5122152,
          -6.9398332
        ]
      },
      "properties": {
        "id": 5355760300,
        "bus": "yes",
        "name": "Cipatik",
        "public_transport": "stop_position"
      }
    },
    {
      "type": "Feature",
      "geometry": {
        "type": "Point",
        "coordinates": [
          107.5587526,
          -6.8971443
        ]
      },
      "properties": {
        "id": 12633822774,
        "bus": "yes",
        "name": "Terminal Cimindi",
        "public_transport": "stop_position"
      }
    }
  ]
}