{
  "type": "FeatureCollection",
  "features": [
    {
      "type": "Feature",
      "geometry": {
        "type": "Point",
        "coordinates": [
          107.6028846,
          -6.934073
        ]
      },
      "properties": {
        "id": 3110064979,
        "bus": "yes",
        "name": "Terminal Tegallega",
        "public_transport": "stop_position"
      }
    },
    {
      "type": "Feature",
      "geometry": {
        "type": "Point",
        "coordinates": [
          107.713347,
          -7.0357328
        ]
      },
      "properties": {
        "id": 2459057875,
        "bus": "yes",
        "name": "Terminal Ciparay",
        "public_transport": "stop_position"
      }
    }
  ]
}