{"type":"FeatureCollection","features":[{"type":"Feature","geometry":{"type":"Point","coordinates":[107.6199195,-6.9011743]},"properties":{"id":1666155324,"bus":"yes","name":"Lapangan Gasibu A","public_transport":"stop_position"}},{"type":"Feature","geometry":{"type":"Point","coordinates":[107.6868117,-6.9655502]},"properties":{"id":2518053983,"bus":"yes","highway":"bus_stop","name":"Simpang Derwati","public_transport":"stop_position"}}]}