{"type":"FeatureCollection","features":[{"type":"Feature","geometry":{"type":"Point","coordinates":[107.5963606,-6.9848701]},"properties":{"id":710309612,"bus":"yes","highway":"bus_stop","name":"Rancamanyar","public_transport":"stop_position"}},{"type":"Feature","geometry":{"type":"Point","coordinates":[107.6235977,-7.0059629]},"properties":{"id":12626499675,"bus":"yes","name":"KEJARI Bale Bandung","public_transport":"stop_position"}}]}