{
  "type": "FeatureCollection",
  "features": [
    {
      "type": "Feature",
      "geometry": {
        "type": "Point",
        "coordinates": [
          107.5890644,
          -6.914151
        ]
      },
      "properties": {
        "id": 3244745033,
        "bus": "yes",
        "name": "Stasiun Ciroyom",
        "public_transport": "stop_position"
      }
    },
    {
      "type": "Feature",
      "geometry": {
        "type": "Point",
        "coordinates": [
          107.5751448,
          -6.8826498
        ]
      },
      "properties": {
        "id": 1585594342,
        "bus": "yes",
        "name": "Pasar Cibogo Sarijadi",
        "public_transport": "stop_position"
      }
    }
  ]
}